first_passage_percolation_sim/__init__.py
first_passage_percolation_sim/fpp.py
first_passage_percolation_sim/fpp.pyi
first_passage_percolation_sim/py.typed
first_passage_percolation_sim-0.1.4.dist-info/METADATA
first_passage_percolation_sim-0.1.4.dist-info/WHEEL
first_passage_percolation_sim-0.1.4.dist-info/licenses/LICENSE
first_passage_percolation_sim-0.1.4.dist-info/RECORD
