Metadata-Version: 2.3
Name: first-passage-percolation-sim
Version: 0.1.4
Summary: Simulations of the first passage percolation on the square lattice
Project-URL: Documentation, https://github.com/arnaud-ma/first-passage-percolation#readme
Project-URL: Issues, https://github.com/arnaud-ma/first-passage-percolation/issues
Project-URL: Source, https://github.com/arnaud-ma/first-passage-percolation
Author-email: arnaud-ma <arnaudma.code@gmail.com>
License-Expression: MIT
License-File: LICENSE
Keywords: first-passage-percolation,graph-theory,percolation,probability,simulation,square-lattice
Classifier: Development Status :: 4 - Beta
Classifier: Programming Language :: Python
Classifier: Programming Language :: Python :: 3.12
Classifier: Programming Language :: Python :: Implementation :: CPython
Requires-Python: >=3.12
Requires-Dist: matplotlib>=3.8
Requires-Dist: numpy>=1.26
Requires-Dist: rustworkx>=0.14
